color_detectron/__init__.py
color_detectron-0.0.1a0.dist-info/LICENSE
color_detectron-0.0.1a0.dist-info/METADATA
color_detectron-0.0.1a0.dist-info/WHEEL
color_detectron-0.0.1a0.dist-info/top_level.txt
color_detectron-0.0.1a0.dist-info/RECORD
