Metadata-Version: 2.1
Name: color-detectron
Version: 0.0.1a0
Summary: placeholder until made opensource
Home-page: https://github.com/cceyda/color-detectron
Author: Ceyda Cinarel
Author-email: snu_ceyda@gmail.com
License: UNKNOWN
Platform: UNKNOWN
Classifier: Programming Language :: Python :: 3
Classifier: License :: OSI Approved :: MIT License
Classifier: Operating System :: OS Independent
Requires-Python: >=3.6
Requires-Dist: pyyaml
Requires-Dist: coloredlogs
